jcnc/__init__.py
jcnc/__main__.py
jcnc/config.yml
jcnc/jcnc.py
jcnc/jcnc.yml
jcnc/main.py
jcnc/resources.py
jcnc/resources.qrc
jcnc/resources_rc.py
jcnc/style.qss
jcnc/ui/jcnc.ui
jcnc/ui/jcnc_ui.py
jcnc/ui/window.ui
jcnc/ui/window_ui.py
jcnc-0.0.2.dist-info/LICENSE.md
jcnc-0.0.2.dist-info/METADATA
jcnc-0.0.2.dist-info/WHEEL
jcnc-0.0.2.dist-info/entry_points.txt
jcnc-0.0.2.dist-info/top_level.txt
jcnc-0.0.2.dist-info/RECORD
