Metadata-Version: 2.1
Name: jcnc
Version: 0.0.2
Summary: Jauria CNC - A QtPyVCP based Virtual Control Panel for LinuxCNC
Home-page: https://github.com/TurBoss/jauriacnc
Author: Jauria Studios
Author-email: 
License: UNKNOWN
Download-URL: https://github.com/TurBoss/jauriacnc/tarball/master
Platform: UNKNOWN
Requires-Dist: qtpyvcp
